{ "subject": "linescore_mlb_2012_04_27_gid_2012_04_27_sdnmlb_sfnmlb_1", "copyright" : "Copyright 2012 MLB Advanced Media, L.P.  Use of any content on this page acknowledges agreement to the terms posted here http://gdx.mlb.com/components/copyright.txt", "data" : {"game":{"home_team_runs":"3","game_type":"R","home_recap_link":"/mlb/gameday/index.jsp?gid=2012_04_27_sdnmlb_sfnmlb_1&mode=recap&c_id=sf","away_time":"7:15","away_preview_link":"/mlb/gameday/index.jsp?gid=2012_04_27_sdnmlb_sfnmlb_1&mode=preview&c_id=mlb","time":"10:15","top_inning":"N","home_time":"7:15","home_team_name":"Giants","ind":"F","original_date":"2012/04/27","home_team_city":"San Francisco","venue_id":"2395","gameday_sw":"P","away_win":"7","home_games_back_wildcard":"3.0","save_pitcher":{"last":"Street","name_display_roster":"Street","era":"1.13","id":"434718","first_name":"Huston","s_losses":"","s_era":"","last_name":"Street","saves":"3","losses":"0","first":"Huston","s_wins":"","wins":"0"},"away_team_id":"135","tz_hm_lg_gen":"ET","status":"Final","home_loss":"10","home_code":"sfn","home_games_back":"4.0","away_sport_code":"mlb","home_win":"10","time_hm_lg":"10:15","away_name_abbrev":"SD","league":"NN","time_zone_aw_lg":"-4","home_file_code":"sf","away_games_back":"7.5","game_data_directory":"/gameday/components/game/mlb/gid_2012_04_27_sdnmlb_sfnmlb_1","time_zone":"ET","away_league_id":"104","preview":"/mlb/gameday/index.jsp?gid=2012_04_27_sdnmlb_sfnmlb_1&mode=preview&c_id=mlb","away_recap_link":"/mlb/gameday/index.jsp?gid=2012_04_27_sdnmlb_sfnmlb_1&mode=recap&c_id=sd","home_team_id":"137","time_aw_lg":"10:15","away_team_city":"San Diego","day":"FRI","tz_aw_lg_gen":"ET","away_code":"sdn","winning_pitcher":{"id":"458537","s_losses":"","first_name":"Cory","s_era":"","last":"Luebke","last_name":"Luebke","losses":"1","era":"2.61","name_display_roster":"Luebke","first":"Cory","s_wins":"","wins":"3"},"game_media":{"media":{"free":"NO","title":"SD @ SF","thumbnail":"http://mediadownloads.mlb.com/mlbam/preview/sdnsfn_318029_th_7_preview.jpg","media_state":"media_archive","start":"2012-04-27T22:15:00-0400","has_mlbtv":"true","calendar_event_id":"14-318029-2012-04-27","type":"game"}},"scheduled_innings":"9","away_games_back_wildcard":"6.5","linescore":[{"away_inning_runs":"1","inning":"1","home_inning_runs":"1"},{"away_inning_runs":"0","inning":"2","home_inning_runs":"0"},{"away_inning_runs":"0","inning":"3","home_inning_runs":"0"},{"away_inning_runs":"2","inning":"4","home_inning_runs":"0"},{"away_inning_runs":"0","inning":"5","home_inning_runs":"1"},{"away_inning_runs":"0","inning":"6","home_inning_runs":"0"},{"away_inning_runs":"2","inning":"7","home_inning_runs":"0"},{"away_inning_runs":"0","inning":"8","home_inning_runs":"1"},{"away_inning_runs":"0","inning":"9","home_inning_runs":"0"}],"venue_w_chan_loc":"USCA0987","away_team_name":"Padres","gameday_link":"2012_04_27_sdnmlb_sfnmlb_1","outs":"3","id":"2012/04/27/sdnmlb-sfnmlb-1","home_name_abbrev":"SF","wrapup_link":"/mlb/gameday/index.jsp?gid=2012_04_27_sdnmlb_sfnmlb_1&mode=wrap&c_id=mlb","ampm":"PM","home_division":"W","home_time_zone":"PT","tv_station":"CSN-BA HD","away_team_errors":"3","away_team_runs":"5","away_time_zone":"PT","hm_lg_ampm":"PM","home_sport_code":"mlb","inning":"9","home_team_hits":"9","inning_state":"","game_pk":"318029","home_ampm":"PM","photos_link":"/mlb/gameday/index.jsp?gid=2012_04_27_sdnmlb_sfnmlb_1&mode=photos","venue":"AT&T Park","home_league_id":"104","away_team_hits":"11","away_loss":"14","home_team_errors":"2","away_file_code":"sd","losing_pitcher":{"id":"459345","s_losses":"","first_name":"Eric","s_era":"","last":"Hacker","last_name":"Hacker","losses":"1","era":"4.50","name_display_roster":"Hacker","first":"Eric","s_wins":"","wins":"0"},"aw_lg_ampm":"PM","home_preview_link":"/mlb/gameday/index.jsp?gid=2012_04_27_sdnmlb_sfnmlb_1&mode=preview&c_id=mlb","time_zone_hm_lg":"-4","away_ampm":"PM","away_division":"W"}}}